twostates/__init__.py
twostates/twostates.py
twostates-0.0.3.dist-info/METADATA
twostates-0.0.3.dist-info/WHEEL
twostates-0.0.3.dist-info/top_level.txt
twostates-0.0.3.dist-info/RECORD
